miappe/__init__.py
miappe/cli/__init__.py
miappe/cli/main.py
miappe/metadata/__init__.py
miappe/metadata/convert.py
miappe/metadata/helpers.py
miappe/metadata/io.py
miappe/metadata/isatools/__init__.py
miappe/metadata/isatools/constants.py
miappe/metadata/isatools/create/__init__.py
miappe/metadata/isatools/create/assay_templates.py
miappe/metadata/isatools/create/connectors.py
miappe/metadata/isatools/create/constants.py
miappe/metadata/isatools/create/errors.py
miappe/metadata/isatools/create/model.py
miappe/metadata/isatools/graphQL/README.md
miappe/metadata/isatools/graphQL/custom_scalars.py
miappe/metadata/isatools/graphQL/inputs.py
miappe/metadata/isatools/graphQL/models.py
miappe/metadata/isatools/graphQL/queries/introspection.gql
miappe/metadata/isatools/graphQL/unions.py
miappe/metadata/isatools/graphQL/utils/filters.py
miappe/metadata/isatools/graphQL/utils/find.py
miappe/metadata/isatools/graphQL/utils/search.py
miappe/metadata/isatools/graphQL/utils/validate.py
miappe/metadata/isatools/io/__init__.py
miappe/metadata/isatools/io/isatab_configurator.py
miappe/metadata/isatools/io/isatab_parser.py
miappe/metadata/isatools/isatab/__init__.py
miappe/metadata/isatools/isatab/defaults.py
miappe/metadata/isatools/isatab/deprecated.py
miappe/metadata/isatools/isatab/dump/__init__.py
miappe/metadata/isatools/isatab/dump/core.py
miappe/metadata/isatools/isatab/dump/utils.py
miappe/metadata/isatools/isatab/dump/write.py
miappe/metadata/isatools/isatab/graph.py
miappe/metadata/isatools/isatab/load/ProcessSequenceFactory.py
miappe/metadata/isatools/isatab/load/__init__.py
miappe/metadata/isatools/isatab/load/core.py
miappe/metadata/isatools/isatab/load/read.py
miappe/metadata/isatools/isatab/utils.py
miappe/metadata/isatools/isatab/validate/__init__.py
miappe/metadata/isatools/isatab/validate/core.py
miappe/metadata/isatools/isatab/validate/rules/__init__.py
miappe/metadata/isatools/isatab/validate/rules/core.py
miappe_api-0.1.0.dist-info/LICENSE
miappe_api-0.1.0.dist-info/METADATA
miappe_api-0.1.0.dist-info/WHEEL
miappe_api-0.1.0.dist-info/entry_points.txt
miappe_api-0.1.0.dist-info/RECORD
